{
  "generated_at": "2026-05-24T15:56:16.125594+00:00",
  "count": 33,
  "influencers": [
    {
      "id": "yt_UCnFFOjljp1_sacTz7PfIIyg",
      "platform": "youtube",
      "channel_id": "UCnFFOjljp1_sacTz7PfIIyg",
      "handle": "@leojmakeup",
      "name": "LeoJ Makeup",
      "description": "메이크업아티스트 레오제이 🖤ARTIST FOREVER 🖤\n재밌게 예쁘고 멋있어지는 방법 😆\n\n– 비지니스 문의 : leojmakeup@lefericreator.com\n– 인스타그램 : https://instagram.com/leojmakeup",
      "profile_url": "https://www.youtube.com/channel/UCnFFOjljp1_sacTz7PfIIyg",
      "profile_image": "https://yt3.ggpht.com/ytc/AIdro_n_prkAS2s-jB2JHHI7g0tstz6iohY_6qBqQ6lxKra2vYg=s800-c-k-c0x00ffffff-no-rj",
      "country": "KR",
      "language": "ko",
      "keywords": "레오제이 LeoJ 남자뷰티크레이터 남자뷰티유튜버 \"잘생긴 남자유튜버\" \"남자 메이크업아티스트\"",
      "followers": 1440000,
      "view_count": 675713081,
      "video_count": 761,
      "avg_views_per_video": 887928,
      "engagement_rate": null,
      "tier": "mega",
      "category": [
        "skincare",
        "beauty"
      ],
      "last_updated": "2026-05-24"
    },
    {
      "id": "yt_UC81bxgGwnjeN7pLPJFci9uw",
      "platform": "youtube",
      "channel_id": "UC81bxgGwnjeN7pLPJFci9uw",
      "handle": "@una_only",
      "name": "UNA 유나",
      "description": "Contact us\nbeautyclouduna@gmail.com",
      "profile_url": "https://www.youtube.com/channel/UC81bxgGwnjeN7pLPJFci9uw",
      "profile_image": "https://yt3.ggpht.com/oVY7TtmU1fNxwDefEzQ-93TpNr-RW0DdhNfLBebYHhx-ug8ps9obKOIWi7PjM8v70HxhDIGMXg=s800-c-k-c0x00ffffff-no-rj",
      "country": "KR",
      "language": "",
      "keywords": "유나 뷰티클라우드 una 미백주스 뱃살주스 스킨케어 홈케어 다이어트 healthy food life skincare korea 유나뷰스터 더유나 theuna 오리지널세럼 \"original serum\" 괴물세럼",
      "followers": 807000,
      "view_count": 75994599,
      "video_count": 176,
      "avg_views_per_video": 431787,
      "engagement_rate": null,
      "tier": "macro",
      "category": [
        "skincare",
        "beauty"
      ],
      "last_updated": "2026-05-24"
    },
    {
      "id": "yt_UCrlUlicedicJ5mlibqC62Eg",
      "platform": "youtube",
      "channel_id": "UCrlUlicedicJ5mlibqC62Eg",
      "handle": "@beautyacne_inssi",
      "name": "뷰드름 유튜버 인씨",
      "description": "트러블+모공+요철, 현실적인 피부 고민을 갖고 있어요🤍\n유튜브에서 못다한 얘기는 인스타그램에서~~~~\n🥨비즈니스 문의 : incworld@goldenwhales.co.kr\n",
      "profile_url": "https://www.youtube.com/channel/UCrlUlicedicJ5mlibqC62Eg",
      "profile_image": "https://yt3.ggpht.com/oKy1i_TqOsdpsf0fBgoPhkw3R2g98PFM_b75evkYOp7WxDdfYLgrSzEnH50bE6lF_De4CvBQEA=s800-c-k-c0x00ffffff-no-rj",
      "country": "KR",
      "language": "",
      "keywords": "메이크업 여드름 뷰드름 뷰드름유튜버 인씨 스킨케어 makeup 모공 \"모공 피부\" \"여드름 피부\" 요철 피부결 베이스 \"베이스 리뷰\" \"쿠션 리뷰\" \"파운데이션 리뷰\" \"신상 쿠션\"",
      "followers": 567000,
      "view_count": 394862641,
      "video_count": 1168,
      "avg_views_per_video": 338067,
      "engagement_rate": null,
      "tier": "macro",
      "category": [
        "skincare",
        "beauty"
      ],
      "last_updated": "2026-05-24"
    },
    {
      "id": "yt_UChaTUCM7bPBTJaIZQ83PNwQ",
      "platform": "youtube",
      "channel_id": "UChaTUCM7bPBTJaIZQ83PNwQ",
      "handle": "@스완_현실남자관리",
      "name": "스완SWAN_현실남자관리",
      "description": "태어난 김에 멋있게 살자\n\n👇진행 중인 할인 & 이벤트들👇\nlink.inpock.co.kr/swan_bgr\n\n*출연&섭외 문의 \nswan.official.creative@gmail.com\n\n*비즈니스문의\nswan.beyondgrooming@bgroom.co.kr \n\n*운영채널\n- 네이버카페 : https://cafe.naver.com/beyondgroomi",
      "profile_url": "https://www.youtube.com/channel/UChaTUCM7bPBTJaIZQ83PNwQ",
      "profile_image": "https://yt3.ggpht.com/ghUeV6_FE7oiT4vn-B6M_mzEK5NClTfF-tV3bFZ1LIH7gRwtUepjGeWWN8QiUGmeh8x9bu3n=s800-c-k-c0x00ffffff-no-rj",
      "country": "KR",
      "language": "",
      "keywords": "스완 SWAN 현실남자뷰티 남자관리 남자뷰티유튜버 남자메이크업",
      "followers": 497000,
      "view_count": 281787402,
      "video_count": 1127,
      "avg_views_per_video": 250033,
      "engagement_rate": null,
      "tier": "macro",
      "category": [
        "skincare",
        "beauty"
      ],
      "last_updated": "2026-05-24"
    },
    {
      "id": "yt_UCVbW7vOtOnmjyDORZB4Sz0w",
      "platform": "youtube",
      "channel_id": "UCVbW7vOtOnmjyDORZB4Sz0w",
      "handle": "@jung__won.k",
      "name": "관리는 하고 살자",
      "description": "우리는 남자들의 건강한 아름다움을 선도합니다\n\n남자 관리의 모든 것 \n\" 관리는 하고 살자 \"\n\n-\nInstagram : jung__won.k\nTik tok :  jung__won.k\nE-mail : kmskjw456@naver.com\n\n비즈니스 메일 부탁드립니다 :)\n",
      "profile_url": "https://www.youtube.com/channel/UCVbW7vOtOnmjyDORZB4Sz0w",
      "profile_image": "https://yt3.ggpht.com/NuFRm1iBv0N3MY_ym0s4S8u-GimwRhzCii4wAuNhXBbLifbW3kFVatJyXq9jZFKMvH3i2n67_g=s800-c-k-c0x00ffffff-no-rj",
      "country": "KR",
      "language": "",
      "keywords": "관리는하고살자 남자관리 남자관리법 남자헤어스타일 남자뷰티 뷰티 관리하는남자 남자머리 뷰티크리에이터 남자고데기 남자눈썹 남자피부 피부좋아지는법 남자헤어스타일링 관리 애즈펌 가르마펌 시스루 포마드 남자머리",
      "followers": 358000,
      "view_count": 178697579,
      "video_count": 598,
      "avg_views_per_video": 298825,
      "engagement_rate": null,
      "tier": "macro",
      "category": [
        "skincare",
        "beauty"
      ],
      "last_updated": "2026-05-24"
    },
    {
      "id": "yt_UCYsv-IHC-B-DiVMmJuqibcg",
      "platform": "youtube",
      "channel_id": "UCYsv-IHC-B-DiVMmJuqibcg",
      "handle": "@jaina0",
      "name": "제이나 [Jaina]",
      "description": "화장품이 너무 좋아서 일도 삶도 화장품 그 자체가 됐어요. \n로레알, 시세이도 NARS, 닥터자르트 마케팅 출신 \n\n현 레이어랩 대표 \n\n나에게 맞는 화장품을 스스로 고를 수 있도록, 브랜드 이야기와 성분 이야기를 쉽고 편안하게 풀어 드리겠습니다. \n\n제이나 채널 문의 : business@jainity.co.kr \n",
      "profile_url": "https://www.youtube.com/channel/UCYsv-IHC-B-DiVMmJuqibcg",
      "profile_image": "https://yt3.ggpht.com/1552c4Wsbd_dixCm_aQ0LC2xhQPoGB9VwIXVlsn95WOQ7yxaVxoh059GQ6WZ8Bk4Jlm6vJ72kw=s800-c-k-c0x00ffffff-no-rj",
      "country": "KR",
      "language": "ko",
      "keywords": "화장품 뷰티 피부관리 \"피부 좋아지는법\" 스킨케어",
      "followers": 283000,
      "view_count": 34594250,
      "video_count": 204,
      "avg_views_per_video": 169580,
      "engagement_rate": null,
      "tier": "macro",
      "category": [
        "skincare",
        "beauty"
      ],
      "last_updated": "2026-05-24"
    },
    {
      "id": "yt_UCdpGQgQ3HOucwR8Wk2wzSHQ",
      "platform": "youtube",
      "channel_id": "UCdpGQgQ3HOucwR8Wk2wzSHQ",
      "handle": "@gggyul",
      "name": "셀프케어 결",
      "description": "𝙒𝙖𝙣𝙣𝙖 𝙙𝙤 𝙛𝙪𝙣 '𝙨𝙚𝙡𝙛𝙘𝙖𝙧𝙚' 𝙬𝙞𝙩𝙝 𝙢𝙚? \n저랑 재미있게 ‘셀프케어' 하실래요?\n",
      "profile_url": "https://www.youtube.com/channel/UCdpGQgQ3HOucwR8Wk2wzSHQ",
      "profile_image": "https://yt3.ggpht.com/XQvI5DE2TFXi-TeVP6YY1LIDUcSgmwUzweo6ewJtm8mpcVHvK1BX0G8JJZ1vg_PvLapF2jt5-g=s800-c-k-c0x00ffffff-no-rj",
      "country": "KR",
      "language": "",
      "keywords": "\"korean facial skin care\" \"스킨케어 김결\" 스킨케어 피부관리 수부지피부 노화피부 건성피부 예민피부 여드름피부 트러블피부 20대피부관리 30대피부관리 40대피부관리 50대피부관리 스킨케어결 김결 \"skincare gyul\" skincare 마사지 괄사 괄사마사지 guasha 이너뷰티 셀프케어 바디케어 탈모 뷰티디바이스 기초제품추천 GRWM 뷰티 꿀팁 제품추천 \"guasha massage\" 아름다움 헤어케어 바디케어 꿀팁 자기관리 \"korean skincare\"",
      "followers": 261000,
      "view_count": 26756281,
      "video_count": 291,
      "avg_views_per_video": 91946,
      "engagement_rate": null,
      "tier": "macro",
      "category": [
        "skincare",
        "beauty"
      ],
      "last_updated": "2026-05-24"
    },
    {
      "id": "yt_UCT6W2AUy8If3fN1OoKIFUsg",
      "platform": "youtube",
      "channel_id": "UCT6W2AUy8If3fN1OoKIFUsg",
      "handle": "@박경열의피부상담소",
      "name": "박경열의 피부상담소",
      "description": "피부 고민은 비슷해도 해결방법은 전부 다릅니다.\n\n“왜 나만 효과가 없을까요?”\n“예전 얼굴로 돌아갈 수 있을까요?”\n15년 동안 진료실에서 가장 많이 들은 질문들입니다.\n\n그래서 저는 \n차트를 보기 전에 '환자의 얼굴'을 보고,\n시술을 말하기 전에 '사람의 이야기'를 들었습니다.\n피부는 숫자보다 삶에 더 가까운 것이니까요.\n\n15년간 환자를 직접 상담해온",
      "profile_url": "https://www.youtube.com/channel/UCT6W2AUy8If3fN1OoKIFUsg",
      "profile_image": "https://yt3.ggpht.com/-rARi3BeAwrTDAWK51Ib44gZTMD_GnVYTGn92tCSX-Fiez6MSngucnrCN6kNvWnibNhwMp5tsw=s800-c-k-c0x00ffffff-no-rj",
      "country": "KR",
      "language": "",
      "keywords": "",
      "followers": 241000,
      "view_count": 18653252,
      "video_count": 91,
      "avg_views_per_video": 204981,
      "engagement_rate": null,
      "tier": "macro",
      "category": [
        "skincare",
        "beauty"
      ],
      "last_updated": "2026-05-24"
    },
    {
      "id": "yt_UC57_jVZTM427hTqYMXf7utA",
      "platform": "youtube",
      "channel_id": "UC57_jVZTM427hTqYMXf7utA",
      "handle": "@you_needn",
      "name": "You need 윤이든",
      "description": "안녕하세요. 뷰티 크리에이터 윤이든입니다 : )\n\nE-mail : youneedn@lefericreator.com\n\ninstagram : you_needn_",
      "profile_url": "https://www.youtube.com/channel/UC57_jVZTM427hTqYMXf7utA",
      "profile_image": "https://yt3.ggpht.com/HL5fWvLmtqaKskzurEP-WcSWjixBBwbuxwzOv2C53wn403V_uZHUrawJpZfw6DW04mOSHlo5FA=s800-c-k-c0x00ffffff-no-rj",
      "country": "KR",
      "language": "",
      "keywords": "윤이든 좁쌀여드름 메이크업 진정스킨케어",
      "followers": 217000,
      "view_count": 51643083,
      "video_count": 697,
      "avg_views_per_video": 74093,
      "engagement_rate": null,
      "tier": "macro",
      "category": [
        "skincare",
        "beauty"
      ],
      "last_updated": "2026-05-24"
    },
    {
      "id": "yt_UCBcMmQ6ASw8nDUq6egjRETg",
      "platform": "youtube",
      "channel_id": "UCBcMmQ6ASw8nDUq6egjRETg",
      "handle": "@enjoycouple_asmr",
      "name": "Enjoycouple_ASMR",
      "description": "Don’t be self-conscious Don’t compare with others\nJust enjoy And love ♥\n\n\n▼ Business contact ▼\nenjoycouple@naver.com\n",
      "profile_url": "https://www.youtube.com/channel/UCBcMmQ6ASw8nDUq6egjRETg",
      "profile_image": "https://yt3.ggpht.com/0W8_yTaejRkzakOpk8c4hBxBXlwiJ8zzJ0b5TwVPXnxCT4d_SBm4qs94lPdEXJ6VlRGkL760=s800-c-k-c0x00ffffff-no-rj",
      "country": "KR",
      "language": "",
      "keywords": "",
      "followers": 145000,
      "view_count": 104150985,
      "video_count": 62,
      "avg_views_per_video": 1679855,
      "engagement_rate": null,
      "tier": "macro",
      "category": [
        "skincare",
        "beauty"
      ],
      "last_updated": "2026-05-24"
    },
    {
      "id": "yt_UCodG0bJ3OICRA1bg4TBdU9A",
      "platform": "youtube",
      "channel_id": "UCodG0bJ3OICRA1bg4TBdU9A",
      "handle": "@피부트래블러",
      "name": "피부트래블러",
      "description": "대한민국 2% 피부과 전문의 14년차 노성민\n\n피부과전문의의 건강한 피부 상담이 필요하시다면,\n📞 02-2296-7007\n\n노성민 원장\n\n· 연세대학교 의과대학 최우등 졸업\n· 연세대학교 의과대학원 피부과학석사\n· 신촌 세브란스 병원 피부과 전공의 수료\n· 서울 병무청 징병전담의사 피부과 과장\n· 전) CNP 차앤박 피부과 원장\n· 전) 리뉴미 피부과 원장",
      "profile_url": "https://www.youtube.com/channel/UCodG0bJ3OICRA1bg4TBdU9A",
      "profile_image": "https://yt3.ggpht.com/kupyUEr4qYZZpiBDp1jbpFGy5QCXlxl1D80v5ainY_k6LQoEQJoYZQtPQerEsajRgEGYXtlw=s800-c-k-c0x00ffffff-no-rj",
      "country": "KR",
      "language": "",
      "keywords": "",
      "followers": 135000,
      "view_count": 17757199,
      "video_count": 497,
      "avg_views_per_video": 35729,
      "engagement_rate": null,
      "tier": "macro",
      "category": [
        "skincare",
        "beauty"
      ],
      "last_updated": "2026-05-24"
    },
    {
      "id": "yt_UCB44fSGXvnBP6CVp10CenPg",
      "platform": "youtube",
      "channel_id": "UCB44fSGXvnBP6CVp10CenPg",
      "handle": "@hyovely",
      "name": "효블리 Hyovely",
      "description": "여쿨 걸친 \"핑크가 잘 받는\" 봄 웜 라이트, 효블리입니다💗\n신상 리뷰/스킨케어/데일리 메이크업/패션/일상 등 을 다루고 있는 채널을 운영하고 있습니다.\n\nk-beauty / beauty / fashion / skincare / dailymakeup / makeup\n\n[Contact mail] hyovely@dmil.kr\n[instagram] @hyo_ve",
      "profile_url": "https://www.youtube.com/channel/UCB44fSGXvnBP6CVp10CenPg",
      "profile_image": "https://yt3.ggpht.com/TXxxAv7aVPAAIxIwGfACtJEs3nCo89YGXYan6Pf_4QqP6hfe08FECnmE7Y_LE4NP1ux-j8Vx=s800-c-k-c0x00ffffff-no-rj",
      "country": "KR",
      "language": "",
      "keywords": "",
      "followers": 125000,
      "view_count": 66397149,
      "video_count": 851,
      "avg_views_per_video": 78023,
      "engagement_rate": null,
      "tier": "macro",
      "category": [
        "skincare",
        "beauty"
      ],
      "last_updated": "2026-05-24"
    },
    {
      "id": "yt_UCV5Q_31yEqkV15Q-AHZWE5A",
      "platform": "youtube",
      "channel_id": "UCV5Q_31yEqkV15Q-AHZWE5A",
      "handle": "@dailyjenna",
      "name": "제나 dailyjenna",
      "description": "민감한 수부지 피부 사용설명서 | 슈퍼 깐깐이가 골라줌✨",
      "profile_url": "https://www.youtube.com/channel/UCV5Q_31yEqkV15Q-AHZWE5A",
      "profile_image": "https://yt3.ggpht.com/TF5-XZbSinvQJwfYixLza2WPcj3tGtF3gSF6dBarQmadJOI-iRS1ZLuJVWA9LchxRHaNKyRJ=s800-c-k-c0x00ffffff-no-rj",
      "country": "KR",
      "language": "",
      "keywords": "데일리 메이크업 일상 브이로그",
      "followers": 106000,
      "view_count": 18166822,
      "video_count": 333,
      "avg_views_per_video": 54555,
      "engagement_rate": null,
      "tier": "macro",
      "category": [
        "skincare",
        "beauty"
      ],
      "last_updated": "2026-05-24"
    },
    {
      "id": "yt_UCQD21s64oRT-RwOCLzGRplg",
      "platform": "youtube",
      "channel_id": "UCQD21s64oRT-RwOCLzGRplg",
      "handle": "@yonseistar",
      "name": "피부고민상담소  신촌연세스타피부과",
      "description": "피부과 전문의가 알려주는 여드름 흉터, 화상 흉터 치료의 모든 것!\n \n당신의 피부 고민을 피부과 전문의 5인이 해결해드립니다. \n\n흉터, 여드름, 여드름흉터, 화상흉터, 문신제거, \n손발톱무좀, 한관종, 비립종, 기미, 색소질환, 튼살 등\n여러분의 모든 피부 고민 신촌 연세스타피부과가 함께합니다. \n\n[신촌연세스타피부과]\n서울 서대문구 신촌로73 테라운드",
      "profile_url": "https://www.youtube.com/channel/UCQD21s64oRT-RwOCLzGRplg",
      "profile_image": "https://yt3.ggpht.com/kWwcznyGdKv7CS6uIcq-rr1ehfR-NGYfELREknXYlVd8Tb3HWI_1GAb_UAxXYW83SwfH0YFS=s800-c-k-c0x00ffffff-no-rj",
      "country": "KR",
      "language": "",
      "keywords": "연세스타피부과 피부고민상담소 피부과전문의 신촌피부과 여드름흉터치료 화상흉터 수술흉터 피부레이저 피부관리법 이상주원장 피부과상담 흉터제거 레이저치료 피부질환 흉터전문병원 켈로이드 손발톱무좀 검버섯제거 안면홍조 딸기코치료 튼살제거 프락셀 핀홀법 레이저토닝 써마지 울쎄라 흉터수술 피부과추천 피부과비용 피부과부작용 여드름흉터없애는법",
      "followers": 62400,
      "view_count": 13116405,
      "video_count": 721,
      "avg_views_per_video": 18192,
      "engagement_rate": null,
      "tier": "mid",
      "category": [
        "skincare",
        "beauty"
      ],
      "last_updated": "2026-05-24"
    },
    {
      "id": "yt_UCd7icqUv7f8k2E6n4WOCIQg",
      "platform": "youtube",
      "channel_id": "UCd7icqUv7f8k2E6n4WOCIQg",
      "handle": "@pibukyurl",
      "name": "피부결",
      "description": "👇영상 속 피부결 추천 제품이 궁금하다면?\n#피부관리 #스킨케어 #홈케어 #자기관리 #피부결\n\n제품보다 루틴이 더 중요하다고 느낀 순간,\n피부결에서 시작해보세요.\n\n피부 좋아지는 법, 생각보다 간단해요.\n기초부터 제대로 쌓아야 피부가 진짜 편안해지거든요.\n\n건조하고 예민한 날씨엔\n피부장벽이 무너지기 쉬워서\n트러블 올라오고, 홍조에 각질까지… 다 흔들리죠.\n",
      "profile_url": "https://www.youtube.com/channel/UCd7icqUv7f8k2E6n4WOCIQg",
      "profile_image": "https://yt3.ggpht.com/uYFbr22nCWUjP21YKKlI7YHZsBlicB4UlxtrH7kXllbz61DH7qfCXijYAUdPu7e76rVHaf_Hjg=s800-c-k-c0x00ffffff-no-rj",
      "country": "KR",
      "language": "ko",
      "keywords": "",
      "followers": 58600,
      "view_count": 5027363,
      "video_count": 70,
      "avg_views_per_video": 71819,
      "engagement_rate": null,
      "tier": "mid",
      "category": [
        "skincare",
        "beauty"
      ],
      "last_updated": "2026-05-24"
    },
    {
      "id": "yt_UCdLeBLR4nEDNwNtmemSOYUg",
      "platform": "youtube",
      "channel_id": "UCdLeBLR4nEDNwNtmemSOYUg",
      "handle": "@anacli_skinguard",
      "name": "아나클리_피부지킴이",
      "description": "주요 피부 고민을 해결하기 위해 끊임없이 연구하고 있습니다.\n20년 경력의 피부과전문의 이상준 원장님이 든든한 피부 지킴이가 되어드리겠습니다!\n\n🔸피지샘(여드름·흉터·모공)\n🔸콜라겐(탄력·주름)\n🔸색소·홍조\n--------------------------------------------\n☎️02) 3420-2201\n카톡상담_ @아름다운나라피부과\n",
      "profile_url": "https://www.youtube.com/channel/UCdLeBLR4nEDNwNtmemSOYUg",
      "profile_image": "https://yt3.ggpht.com/ujgswaDyOhG7E46AQurw18A4pMb7HsKPsyEIImSvzxtyPkB-PttFLyRFAvP6O76hLyzhBCTPQFU=s800-c-k-c0x00ffffff-no-rj",
      "country": "KR",
      "language": "",
      "keywords": "피부과전문의 의학박사 강남피부과 이상준원장 이상준피부과 아름다운나라피부과 의사유튜버 medicalchennel 의학정보",
      "followers": 30600,
      "view_count": 4131927,
      "video_count": 208,
      "avg_views_per_video": 19865,
      "engagement_rate": null,
      "tier": "micro",
      "category": [
        "skincare",
        "beauty"
      ],
      "last_updated": "2026-05-24"
    },
    {
      "id": "yt_UCWmuQwMZKKqGK9KM3MSXypw",
      "platform": "youtube",
      "channel_id": "UCWmuQwMZKKqGK9KM3MSXypw",
      "handle": "@skincare5602",
      "name": "온라인스킨케어",
      "description": "안녕하세요\n\n피부는 결국 우리가 매일 어떻게 나를 돌보느냐의 결과입니다.\n보톡스 없이도 아름답게 자연스럽게 나이 드는 법 이곳에서 함께 배워가요.\n\n\n",
      "profile_url": "https://www.youtube.com/channel/UCWmuQwMZKKqGK9KM3MSXypw",
      "profile_image": "https://yt3.ggpht.com/leCkraiZx9dZxaJRtf1aAbof8g-hoMbuORLNYT9bJMJQg03YX8l1Sm5MDORzxipQ_FvUei0MPw=s800-c-k-c0x00ffffff-no-rj",
      "country": "KR",
      "language": "",
      "keywords": "#피부관리 #화장품 #마스크팩 #오일 #올리브영 #선크림 #틴트 #립스틱 #립밤 #세럼 #에센스 #수분크림 #재생크림 #천연오일 #바디오일 #오일밤 #바이오셀룰로우스 #바디팩 #클렌저 #각질제거 #세안제 #피부과 #기미 #검버섯 #주름제거 #주름 #홈케어 #화이트닝 #미백 #미용기기 #부스터프로 #디바이스 #토너 #기초화장품 #홍조 #여드름 #보톡스 #필러 #시술 #스킨 #색소침착 #흑자 #레이저 #리쥬란 #울쎄라 #인모드 #발각질",
      "followers": 28100,
      "view_count": 6578076,
      "video_count": 207,
      "avg_views_per_video": 31778,
      "engagement_rate": null,
      "tier": "micro",
      "category": [
        "skincare",
        "beauty"
      ],
      "last_updated": "2026-05-24"
    },
    {
      "id": "yt_UCEQoaBLdg6tZQVMFxVlleIw",
      "platform": "youtube",
      "channel_id": "UCEQoaBLdg6tZQVMFxVlleIw",
      "handle": "@jennysbeautytips",
      "name": "홈케어는 제니언니",
      "description": "화장품을 무조건 많이 산다고 해서\n인플루언서가 광고/추천한 제품을 쓴다고 해서\n피부가 좋아지는 게 아닙니다.\n\n하나를 쓰더라도 원리, 순서, 방법을 제대로 알고 쓰면\n더 적은 돈을 쓰고도\n피부가 더 빨리 더 확실하게 좋아집니다.\n\n지난 14년간 집에서 직접 홈케어를 하며 깨달은 원리들,\n그리고 화장품 전문가 교육을 통해 계속 업데이트 중인 지식들,\n여기에 ",
      "profile_url": "https://www.youtube.com/channel/UCEQoaBLdg6tZQVMFxVlleIw",
      "profile_image": "https://yt3.ggpht.com/DIW-rUHfm_FB6daoUi0OwTMphNED272zUcJ6MILVMInaqr11SpZFyQSLAjRlNsB0nhuIg4Y7BAE=s800-c-k-c0x00ffffff-no-rj",
      "country": "KR",
      "language": "",
      "keywords": "",
      "followers": 19500,
      "view_count": 1918760,
      "video_count": 151,
      "avg_views_per_video": 12707,
      "engagement_rate": null,
      "tier": "micro",
      "category": [
        "skincare",
        "beauty"
      ],
      "last_updated": "2026-05-24"
    },
    {
      "id": "yt_UCbwZT-nzD2tj3mgY6hGwXeg",
      "platform": "youtube",
      "channel_id": "UCbwZT-nzD2tj3mgY6hGwXeg",
      "handle": "@drbaeskin",
      "name": "Dr.Bae의 피부이야기 배Skin",
      "description": "안녕하세요. 피부과전문의 배병기입니다. \n\nDr.Bae의 피부이야기 배Skin은 가벼운 피부고민에서부터 미용시술에 대한 이야기까지 피부에 대한 모든 이야기를 하고자 합니다. \n\nDr.Bae의 피부이야기 배Skin은 항상 정직하고, 정확하고, 깊이있는 이야기를 드리기 위해 최선을 다하겠습니다.\n\n감사합니다.",
      "profile_url": "https://www.youtube.com/channel/UCbwZT-nzD2tj3mgY6hGwXeg",
      "profile_image": "https://yt3.ggpht.com/CiahBOHew8nAWU3iduxKikAeNO2-rTCu6d96QdDXqHV86ZkmahUh1sHw0pKqLSwkb-XNkPCBAA=s800-c-k-c0x00ffffff-no-rj",
      "country": "KR",
      "language": "",
      "keywords": "피부과전문의 피부과 배병기원장 스컬트라 보톡스 레이저 필러 엘란쎄 콜라움 피부 주름 모공 화장품 홈케어 관리 쥬베룩 탄력 팔자 미간 고주파 이너뷰티 콜라겐 배스킨 배Skin 피부관리 피부정보 의사 닥터배 시술 강남피부과 피부과추천 아쿠아필 여드름 리프팅 프락셀 피부맛집 피부시술 물광주사 스킨부스터 피부과관리 피부과재생크림 피부과레이저 피부과잘하는곳 피부과앰플 피부과크림 약국템",
      "followers": 18400,
      "view_count": 10524544,
      "video_count": 337,
      "avg_views_per_video": 31230,
      "engagement_rate": null,
      "tier": "micro",
      "category": [
        "skincare",
        "beauty"
      ],
      "last_updated": "2026-05-24"
    },
    {
      "id": "yt_UCekEudsdDmI7R_0FelfJWaQ",
      "platform": "youtube",
      "channel_id": "UCekEudsdDmI7R_0FelfJWaQ",
      "handle": "@mts전도사",
      "name": "MTS전도사",
      "description": "가장 와닿고 실천 가능한 현실적인 피부 개선 방법 소개,\n오프라인 피부 교육\n",
      "profile_url": "https://www.youtube.com/channel/UCekEudsdDmI7R_0FelfJWaQ",
      "profile_image": "https://yt3.ggpht.com/3cJBdnil1C6WcIWRxat-RLVna-STtjvcPovnTlgECGp9sRXfZG9kdBv5DEn_xfir-8xoxKMkuEE=s800-c-k-c0x00ffffff-no-rj",
      "country": "KR",
      "language": "",
      "keywords": "여드름 트러블피부 피부상담 진정관리 온스식피부관리 미백 홍조 민감 예민피부 마스크팩 염증성여드름 좁쌀여드름 수분크림 미백크림 각질제거 보습 피부보습 세라마이드 수부지 수분부족형지성피부 아르간오일 호호바오일 레티놀 계면활성제 우츠키식피부관리 물세안 프락셀 중간보습 오일보습 아침물세안 이중세안 아이밤 페이스밤 각질제거팩 노푸 미네랄오일 모공수축 모공축소 블랙헤드",
      "followers": 17300,
      "view_count": 6753964,
      "video_count": 1009,
      "avg_views_per_video": 6694,
      "engagement_rate": null,
      "tier": "micro",
      "category": [
        "skincare",
        "beauty"
      ],
      "last_updated": "2026-05-24"
    },
    {
      "id": "yt_UCvLz6NDDmx2zE3ublZoT9MQ",
      "platform": "youtube",
      "channel_id": "UCvLz6NDDmx2zE3ublZoT9MQ",
      "handle": "@olive.beautyuniv",
      "name": "올리의 뷰티대학 -  피부 탐구 채널",
      "description": "\n올리의 뷰티대학 채널에서는\n✔사람들의 피부 고민을 듣고,\n✔원인과 해결 방법을 탐구하며\n✔더 나은 선택을 할 수 있도록\n    올바른 정보를 전달합니다.\n\n피부고민, 궁금증, 원하는 어떤 것이든 알려주세요.\n올리는 언제나 여러분의 목소리를 기다립니다 :)\n\n",
      "profile_url": "https://www.youtube.com/channel/UCvLz6NDDmx2zE3ublZoT9MQ",
      "profile_image": "https://yt3.ggpht.com/n3Qt-tfy3cwqBx9EDq_E61qr7x-S5I75Q_RXa16jnHajvJBejbJJOEqR_-CSiblgnUs_DzBmZOA=s800-c-k-c0x00ffffff-no-rj",
      "country": "KR",
      "language": "",
      "keywords": "",
      "followers": 17300,
      "view_count": 18991548,
      "video_count": 52,
      "avg_views_per_video": 365222,
      "engagement_rate": null,
      "tier": "micro",
      "category": [
        "skincare",
        "beauty"
      ],
      "last_updated": "2026-05-24"
    },
    {
      "id": "yt_UC0IiRuu05k9HorF0GGWVodw",
      "platform": "youtube",
      "channel_id": "UC0IiRuu05k9HorF0GGWVodw",
      "handle": "@ginaparkedtoslay",
      "name": "지나 GINA",
      "description": "논문 읽는 뷰티 크리에이터 지나🧪과학기반 스킨케어\n머리 아픈 논문은 제가 읽을게요 –\n여러분은 그냥 예뻐지고 멋있어지세요!\n\n비지니스 : ginapark@tammikorea.com",
      "profile_url": "https://www.youtube.com/channel/UC0IiRuu05k9HorF0GGWVodw",
      "profile_image": "https://yt3.ggpht.com/a6WRLs6QGC_ywlyR7o1L4w0hYbUg9O0-28u6mChO0jsLdrVJNfKRdYaWWkSK7GpuY8C7NAM8vQ=s800-c-k-c0x00ffffff-no-rj",
      "country": "KR",
      "language": "ko",
      "keywords": "과학기반스킨케어 증거기반스킨케어 화장품성분 성분분석 스킨케어정보 스킨케어팁 스킨케어루틴 레티날 비타민C 논문기반스킨케어 피부과학 블랙헤드 피지필라멘트 좁쌀여드름 티아미돌",
      "followers": 15800,
      "view_count": 2927225,
      "video_count": 147,
      "avg_views_per_video": 19913,
      "engagement_rate": null,
      "tier": "micro",
      "category": [
        "skincare",
        "beauty"
      ],
      "last_updated": "2026-05-24"
    },
    {
      "id": "yt_UCvmrt-GOa-bJt_0aCd8z1Fg",
      "platform": "youtube",
      "channel_id": "UCvmrt-GOa-bJt_0aCd8z1Fg",
      "handle": "@shinjiyn",
      "name": "지연쌤의 피부참견",
      "description": "피부 고민, 이제 혼자 고민하지 마세요!⚪\n\n건강하지 못한 피부는 티가 납니다\n거울 속 내 얼굴이 예전 같지 않은 이유\n피부가 유난히 예민해진 이유\n누군가에게 “요즘 피곤해 보여”라는 말을 듣는 이유도\n대부분 피부에서 시작됩니다\n\n하지만,\n스킨 하나, 세안 습관 하나만 바꿔도\n피부는 생각보다 빠르게 반응합니다\n작은 변화가 표정과 분위기까지 바뀌는 걸\n피부과",
      "profile_url": "https://www.youtube.com/channel/UCvmrt-GOa-bJt_0aCd8z1Fg",
      "profile_image": "https://yt3.ggpht.com/m_Hd3oJ-n6oI8Xax66_9DkPzUCRRuddo0gIcF9D_LWJjnXNhvkehahsp2oxApj4t-dNJejTJ=s800-c-k-c0x00ffffff-no-rj",
      "country": "KR",
      "language": "",
      "keywords": "피부과 피부관리 스킨케어",
      "followers": 15500,
      "view_count": 2089920,
      "video_count": 86,
      "avg_views_per_video": 24301,
      "engagement_rate": null,
      "tier": "micro",
      "category": [
        "skincare",
        "beauty"
      ],
      "last_updated": "2026-05-24"
    },
    {
      "id": "yt_UC6Z_wsj0tNT40IlEo1n0YNw",
      "platform": "youtube",
      "channel_id": "UC6Z_wsj0tNT40IlEo1n0YNw",
      "handle": "@leehaskincare",
      "name": "여드름성지-리하스킨케어",
      "description": "여드름압출•경락전문\n1대1관리,18년차 원장,100%예약제\n\n✔️리하스킨케어\nhttps://naver.me/5xlwXiIM\n✔️인스타그램\nhttps://www.instagram.com/hooddumom\n✔️블로그\nhttps://m.blog.naver.com/leehaskin\n▪️1대1 원장 집중관리,100%예약제\n▪️위치 : 네이버 ➡️ 리하스킨케어 검색\n",
      "profile_url": "https://www.youtube.com/channel/UC6Z_wsj0tNT40IlEo1n0YNw",
      "profile_image": "https://yt3.ggpht.com/hFWYjewGoyeP-sGyc9R_D18QimMvMtVnUS7ETN8EzcQGAKKxynD1qn07GagZ5-btmLURJbo9xCI=s800-c-k-c0x00ffffff-no-rj",
      "country": "KR",
      "language": "ko",
      "keywords": "여드름압출 blackhead \"Acne extrusion\" ニキビ圧出 สิวไหลออกมา \"Acne extrusionem\" 피르가즘 귀르가즘 여드름 \"여드름신 리하\" 리하스킨케어 \"여드름신 leeha\" 피부관리실 좁쌀여드름 피지제거 블랙헤드 코블랙헤드 화이트헤드 피지낭종 귀여드름 прыщ прыщик 青春痘 痤疮 挤出 \"Mụn trứng cá\" Akne L'acné \"El acné\" 피부관리 스킨케어 브이로그 일상 개 멍멍이 골든두들 뚜둥이",
      "followers": 14000,
      "view_count": 22471501,
      "video_count": 718,
      "avg_views_per_video": 31297,
      "engagement_rate": null,
      "tier": "micro",
      "category": [
        "skincare",
        "beauty"
      ],
      "last_updated": "2026-05-24"
    },
    {
      "id": "yt_UCzbxkP1MJil_j9ARuTIznuw",
      "platform": "youtube",
      "channel_id": "UCzbxkP1MJil_j9ARuTIznuw",
      "handle": "@skinstein",
      "name": "피부슈타인",
      "description": "* 애띠애 피부관리 문의\n연락처 : 010-8013-8262 / 031-206-8262\n\n* 카카오톡 문의(피부고민, 교육문의, 제품문의는 카톡 문의에 남겨주세요)\nhttp://pf.kakao.com/_xhVjdC/chat\n\n* 골근동안교육, 여드름교육, 문제성 피부교육, 피부관리실 창업 문의\n010-3333-8161\n",
      "profile_url": "https://www.youtube.com/channel/UCzbxkP1MJil_j9ARuTIznuw",
      "profile_image": "https://yt3.ggpht.com/PKYSKIgVYIWvCXegQYQRlQnIIHMjDauzp7LJKZXPAHdxy85sc7GxTEJEfV0P5ogE2fJz0f37nA=s800-c-k-c0x00ffffff-no-rj",
      "country": "KR",
      "language": "",
      "keywords": "피부슈타인 피부관리 여드름 경락 윤곽관리 피부 강선자 수원피부관리 에스테틱 근처피부관리 얼굴비대칭 얼굴경락 40대피부 피부관리추천 피부노화 피부좋아지는법",
      "followers": 12200,
      "view_count": 1466731,
      "video_count": 243,
      "avg_views_per_video": 6036,
      "engagement_rate": null,
      "tier": "micro",
      "category": [
        "skincare",
        "beauty"
      ],
      "last_updated": "2026-05-24"
    },
    {
      "id": "yt_UC777OVX_laqRC4n7OvQd9fQ",
      "platform": "youtube",
      "channel_id": "UC777OVX_laqRC4n7OvQd9fQ",
      "handle": "@ihatetrouble",
      "name": "피부고민있서영?",
      "description": "화장품에 수억을 쓸 정도로 진심인 제가,\n직접 써보고 효과 본 찐-꿀템만 소개해드려요! 💖\n\n10년 넘게 여드름으로 고생하던 제가 시술 없이 물광 피부가 된 비결, 궁금하지 않으세요?\n✔️ 초예민·민감 피부도 살아남을 수 있는 스킨케어의 모든 것!\n✔️ 현실적이고 효과적인 솔루션!\n\n💼 화장품 회사 대표 & 에스테틱 컨설턴트 출신이 직접 알려드리는 실패 없",
      "profile_url": "https://www.youtube.com/channel/UC777OVX_laqRC4n7OvQd9fQ",
      "profile_image": "https://yt3.ggpht.com/diWQkmmrovS3j7KDl8ME3zMP-0QcyXFIWs58IEbjcO2Y8KzD102K5vDqucbB58NY_QWcFDkwbw=s800-c-k-c0x00ffffff-no-rj",
      "country": "KR",
      "language": "",
      "keywords": "피부 \"물광 피부\" \"피부 관리\" 스킨케어 뷰티 \"화장품 추천\" \"보습 크림\" \"기초 화장품\" beauty skincare 미백화장품 백화점화장품 럭셔리화장품 kbeauty 수분크림 앰플추천 세럼추천 피부좋아지는법 환절기피부",
      "followers": 6740,
      "view_count": 1219701,
      "video_count": 256,
      "avg_views_per_video": 4764,
      "engagement_rate": null,
      "tier": "nano",
      "category": [
        "skincare",
        "beauty"
      ],
      "last_updated": "2026-05-24"
    },
    {
      "id": "yt_UCBpPKxbaUtEFHOYlKD7bfHA",
      "platform": "youtube",
      "channel_id": "UCBpPKxbaUtEFHOYlKD7bfHA",
      "handle": "@on_lina0",
      "name": "온리나 ONLYME",
      "description": "뭘 발라도 따갑고 트러블만 생기시나요? 😶‍🌫️\n온리나 ONLYME | Only 나를 위한 스킨케어\n스킨케어 덕후 간호사가 알려드리는\n내 피부에 딱 맞는 루틴 찾기 🤍\n\n비즈니스 문의: omocana99@gmail.com\n",
      "profile_url": "https://www.youtube.com/channel/UCBpPKxbaUtEFHOYlKD7bfHA",
      "profile_image": "https://yt3.ggpht.com/C5mE0NOCaU_ytFMkgQXV4OwvsuZR8whJ56zSQ-fZFxtsBvjy27xwzthrG-vcP2gxsRxqqmwYf7E=s800-c-k-c0x00ffffff-no-rj",
      "country": "KR",
      "language": "",
      "keywords": "피부관리 피부 여드름 민감성피부 스킨케어 스킨케어루틴 피부좋아지는법",
      "followers": 4550,
      "view_count": 832820,
      "video_count": 66,
      "avg_views_per_video": 12618,
      "engagement_rate": null,
      "tier": "nano",
      "category": [
        "skincare",
        "beauty"
      ],
      "last_updated": "2026-05-24"
    },
    {
      "id": "yt_UCCqJGpSTh2L7v-f64HZI-bw",
      "platform": "youtube",
      "channel_id": "UCCqJGpSTh2L7v-f64HZI-bw",
      "handle": "@에즈윤asyun-w7d",
      "name": "에즈윤 | 민감피부 케어꿀팁",
      "description": "민감성 피부에게 희망을!",
      "profile_url": "https://www.youtube.com/channel/UCCqJGpSTh2L7v-f64HZI-bw",
      "profile_image": "https://yt3.ggpht.com/Cmjcgo8LMLvmMmnSjh5Mgcf8eTLnNaNSXp2c78PEpVjgefcg5jP5rCIgfyfFtQPiTHLUczxQ=s800-c-k-c0x00ffffff-no-rj",
      "country": "KR",
      "language": "",
      "keywords": "",
      "followers": 3330,
      "view_count": 376817,
      "video_count": 44,
      "avg_views_per_video": 8564,
      "engagement_rate": null,
      "tier": "nano",
      "category": [
        "skincare",
        "beauty"
      ],
      "last_updated": "2026-05-24"
    },
    {
      "id": "yt_UCqt1ri48VA36lgKTd4kC4SA",
      "platform": "youtube",
      "channel_id": "UCqt1ri48VA36lgKTd4kC4SA",
      "handle": "@민감성피부",
      "name": " 피부꿀팁은 - 스킨케어룸",
      "description": "*경력사항*\nMBC아카데미 뷰티스쿨 피부미용메이크업 수료\n국가기술피부미용사자격증 취득\n전) 피부관리샵 &피지오더미 스파 테라피스트\n전) 엘카코리아  달팡브랜드 스킨케어테라피스트\n전) 라프레리 스킨케어테라피스트 ( 청담라운지소속)\n그외 백화점 브랜드 산타마리아노벨라 , 샹테카이브랜드 ( 스킨케어 파트)\n전) 차앤박 피부과의원  피부파트\n개인피부과 의원  피부",
      "profile_url": "https://www.youtube.com/channel/UCqt1ri48VA36lgKTd4kC4SA",
      "profile_image": "https://yt3.ggpht.com/STXyQJfghMO5tGNsSMjLPV4BIvg6PKoHVatA9pI-Gvnn-AUqP04d-gu3WnOJkT7NB3ThfjCt83g=s800-c-k-c0x00ffffff-no-rj",
      "country": "KR",
      "language": "",
      "keywords": "",
      "followers": 2810,
      "view_count": 1112323,
      "video_count": 142,
      "avg_views_per_video": 7833,
      "engagement_rate": null,
      "tier": "nano",
      "category": [
        "skincare",
        "beauty"
      ],
      "last_updated": "2026-05-24"
    },
    {
      "id": "yt_UCXV1ISGednuERzhoI8e6f7Q",
      "platform": "youtube",
      "channel_id": "UCXV1ISGednuERzhoI8e6f7Q",
      "handle": "@cafetipfromrosie",
      "name": "Cafetip from rosie 카페팁 프롬 로지",
      "description": "𝙈𝙤𝙫𝙚𝙙 𝙗𝙖𝙘𝙠 𝙛𝙧𝙤𝙢 🇨🇦 𝙩𝙤 𝙨𝙩𝙖𝙧𝙩 𝙖 𝙘𝙖𝙛𝙚 𝙞𝙣 🇰🇷\n☕️현직 카페 사장이 알려주는 커피의 모.든.것.\n🍯스타벅스 꿀팁s 와 카페 레시피 매주 업로드\n📧Business📧: 𝗯𝗶𝘇@𝗱𝗼𝗼𝗵𝗼𝗰𝗼𝗿𝗽.𝗰𝗼𝗺\n\n\n❣️My Instagram:\n: @cafetip.from.rosie\n",
      "profile_url": "https://www.youtube.com/channel/UCXV1ISGednuERzhoI8e6f7Q",
      "profile_image": "https://yt3.ggpht.com/1Y6whfRAYwIapKYClV2p3xZnFmuMmtZggbhkFnYatc2RPzvm6CtpwlRc0zv3o-qHp6NTsEbKyw=s800-c-k-c0x00ffffff-no-rj",
      "country": "KR",
      "language": "",
      "keywords": "rozley!;rozley:real rozely \"캐나다 워킹홀리데이\" 캐나다워홀 \"밴쿠버 워홀\" \"밴쿠버 워킹홀리데이\" 어학연수 캐나다어학연수 \"캐나다 어학연수\" \"캐나다 브이로그\" workingholiday 리얼로즐리 realrozley 토론토 캐나다 밴쿠버 canada vancouver 캐나다브이로그 밴쿠버브이로그 브이로그 영어브이로그 워킹홀리데이 카페사장 카페 카페추천 카페브이로그 카페사장브이로그 홈카페 카페메뉴 스타벅스 스타벅스커스텀",
      "followers": 2790,
      "view_count": 1575457,
      "video_count": 67,
      "avg_views_per_video": 23514,
      "engagement_rate": null,
      "tier": "nano",
      "category": [
        "skincare",
        "beauty"
      ],
      "last_updated": "2026-05-24"
    },
    {
      "id": "yt_UCIH_Box_GnlZ-iTg6H9Y-hg",
      "platform": "youtube",
      "channel_id": "UCIH_Box_GnlZ-iTg6H9Y-hg",
      "handle": "@dr.dj-tomorrowskin",
      "name": "닥터동주의 내일피부",
      "description": "'내일의 나'를 위한 건강한 피부가이드🔎\n안녕하세요. 내일피부의 피부과 전문의 김동주 원장입니다.\n\n대한민국 피부과 전체 의사 중 단 2%인\n'피부과 전문의'라는 자격에 걸맞는 책임감과 지식으로\n여러분의 피부 건강을 책임지겠습니다.\n\n피부 고민에 대해 궁금하신 내용이 있다면 댓글로 남겨주세요!\n피부과전문의 닥터동주가 '직접' 답변드리겠습니다. \n\n✅ 외부 ",
      "profile_url": "https://www.youtube.com/channel/UCIH_Box_GnlZ-iTg6H9Y-hg",
      "profile_image": "https://yt3.ggpht.com/h3xw_EKgUgL6Dkf9A3s-g-bYYhFGp9QJeddYLanUpvo1zw537D5Wi81XImFOZVaWJJrkvaIbWLk=s800-c-k-c0x00ffffff-no-rj",
      "country": "KR",
      "language": "",
      "keywords": "피부과전문의 피부과 피부과추천 스킨부스터 콜라겐부스터 리프팅 닥터스피부과 닥터동주 동안피부 추천시술 피부과가성비 여드름흉터 흉터레이저 흉터치료 위례피부과 김동주 김동주원장 팔자주름 마리오넷주름 주름제거 기미 여드름 흑자",
      "followers": 2390,
      "view_count": 469232,
      "video_count": 155,
      "avg_views_per_video": 3027,
      "engagement_rate": null,
      "tier": "nano",
      "category": [
        "skincare",
        "beauty"
      ],
      "last_updated": "2026-05-24"
    },
    {
      "id": "yt_UC09t8FuhpsebTldz-vp6cgg",
      "platform": "youtube",
      "channel_id": "UC09t8FuhpsebTldz-vp6cgg",
      "handle": "@skincarehailey",
      "name": "스킨케어멘토 헤일리",
      "description": "솔직하고 깊이있는 스킨케어 이야기를 나눠요❤️\n\n10년간 국내외에서 여러 브랜드의 수출과 마케팅을 담당해 오며, \n다양한 뷰티 시장에서 깊이 있는 경험을 쌓아왔습니다.\n\n이제 그동안의 전문성과 경험을 바탕으로, \n스킨케어와 화장품에 관한 유익한 정보를 나누고자 합니다.\n현장에서 얻은 인사이트와 트렌드 분석, \n제품 선택 팁까지 실용적인 정보를 전해드리며, ",
      "profile_url": "https://www.youtube.com/channel/UC09t8FuhpsebTldz-vp6cgg",
      "profile_image": "https://yt3.ggpht.com/lYRD0udTm_KRHhO9ptKnLciHRG1gAVJyqN3oLullIZ7fzUPwrH81fKH0SdXCXWKulRdu7RGjKg=s800-c-k-c0x00ffffff-no-rj",
      "country": "KR",
      "language": "",
      "keywords": "스킨케어 \"스킨케어 추천\" \"스킨케어 루틴\" \"스킨케어 하는법\" \"화장품 추천\" 홈케어 \"홈케어 피부관리\" \"홈케어 루틴\" 피부관리 피부관리법 \"피부관리 루틴\" \"선크림 추천\" \"화장품 성분\"",
      "followers": 1330,
      "view_count": 935339,
      "video_count": 21,
      "avg_views_per_video": 44540,
      "engagement_rate": null,
      "tier": "nano",
      "category": [
        "skincare",
        "beauty"
      ],
      "last_updated": "2026-05-24"
    },
    {
      "id": "yt_UCNwtctL2og4McnQvPeieRgA",
      "platform": "youtube",
      "channel_id": "UCNwtctL2og4McnQvPeieRgA",
      "handle": "@skintrainersoo",
      "name": "피부 트레이너, 피부상담소",
      "description": "루틴 건강 인내 절제 내적충만감을 지향합니다\n\n떼우기 식이 아닌 몸의 건강회복을 통한\n본질적인 피부고민해결을 추구합니다\n\n17년차 피부과 전문의\n운동 중독자\n고려대 의대\n\n채널/협업/인터뷰 관련 문의: wooidding@naver.com \n\n\n\n",
      "profile_url": "https://www.youtube.com/channel/UCNwtctL2og4McnQvPeieRgA",
      "profile_image": "https://yt3.ggpht.com/78rpSuFAuiUX_OPV0hMzTNw2--5ptzo1KaMumMM8m6-wtRcFgX79g-AxZAZC79avkHi_fGE5=s800-c-k-c0x00ffffff-no-rj",
      "country": "KR",
      "language": "",
      "keywords": "피부과전문의 피부병원 피부트러블 홍조 써마지 울쎄라 평촌수피부과 오가나",
      "followers": 1160,
      "view_count": 331565,
      "video_count": 348,
      "avg_views_per_video": 953,
      "engagement_rate": null,
      "tier": "nano",
      "category": [
        "skincare",
        "beauty"
      ],
      "last_updated": "2026-05-24"
    }
  ]
}